README.rst
ec2_meta_env.py
setup.cfg
setup.py
ec2_meta_env.egg-info/PKG-INFO
ec2_meta_env.egg-info/SOURCES.txt
ec2_meta_env.egg-info/dependency_links.txt
ec2_meta_env.egg-info/entry_points.txt
ec2_meta_env.egg-info/requires.txt
ec2_meta_env.egg-info/top_level.txt