Metadata-Version: 1.1
Name: ec2-meta-env
Version: 0.1.1
Summary: A simple package to manifest EC2 instance metadata as environment variables.
Home-page: https://github.com/tobiasmcnulty/ec2-meta-env
Author: Tobias McNulty
Author-email: tobias.mcnulty@gmail.com
License: MIT
Keywords: Python,Python3
Platform: UNKNOWN
Classifier: Development Status :: 6 - Mature
Classifier: Intended Audience :: Developers
Classifier: Natural Language :: English
Classifier: Environment :: Console
Classifier: License :: OSI Approved :: MIT License
Classifier: Programming Language :: Python
Classifier: Programming Language :: Python :: 2
Classifier: Programming Language :: Python :: 2.7
Classifier: Programming Language :: Python :: 3
Classifier: Programming Language :: Python :: 3.4
Classifier: Programming Language :: Python :: 3.5
Classifier: Topic :: Software Development :: Libraries
Classifier: Topic :: Utilities
